rdreturnpurchase/EcsInterface.py
rdreturnpurchase/__init__.py
rdreturnpurchase/mainModel.py
rdreturnpurchase/metadata.py
rdreturnpurchase/operation.py
rdreturnpurchase/utility.py
rdreturnrequest/EcsInterface.py
rdreturnrequest/__init__.py
rdreturnrequest/mainModel.py
rdreturnrequest/metadata.py
rdreturnrequest/operation.py
rdreturnrequest/utility.py
rdreturnpurchase-1.1.7.dist-info/METADATA
rdreturnpurchase-1.1.7.dist-info/WHEEL
rdreturnpurchase-1.1.7.dist-info/top_level.txt
rdreturnpurchase-1.1.7.dist-info/RECORD
